pyOneFichierClient/__main__.py
pyOneFichierClient/test_cli.py
pyOneFichierClient/OneFichierAPI/__init__.py
pyOneFichierClient/OneFichierAPI/exceptions.py
pyOneFichierClient/OneFichierAPI/objects.py
pyOneFichierClient/OneFichierAPI/py1FichierClient.py
pyOneFichierClient/setToken/__main__.py
pyOneFichierClient-1.0.4.dist-info/METADATA
pyOneFichierClient-1.0.4.dist-info/WHEEL
pyOneFichierClient-1.0.4.dist-info/top_level.txt
pyOneFichierClient-1.0.4.dist-info/RECORD
