Metadata-Version: 2.1
Name: pyOneFichierClient
Version: 1.0.4
Summary: The coolest (and probably only for now) API on PyPI for 1ficher API access
Home-page: https://github.com/spookyahell/pyOneFichierClient
Author: That Dude You Don't Want In Your Home
Author-email: vidner123@gmail.com
License: MIT
Download-URL: https://codeload.github.com/spookyahell/pyOneFichierClient/tar.gz/master
Keywords: 1FICHIER,API,CLIENT,FILEHOST
Platform: UNKNOWN
Classifier: Development Status :: 3 - Alpha
Classifier: Intended Audience :: Developers
Classifier: Topic :: Software Development :: Build Tools
Classifier: License :: OSI Approved :: MIT License
Classifier: Programming Language :: Python :: 3
Classifier: Programming Language :: Python :: 3.6
Classifier: Programming Language :: Python :: 3.7
Requires-Dist: requests
